videoIpynbRenderer/__init__.py
videoIpynbRenderer/customException.py
videoIpynbRenderer/logger.py
videoIpynbRenderer/youtube.py
videoIpynbRenderer-0.0.2.dist-info/LICENSE
videoIpynbRenderer-0.0.2.dist-info/METADATA
videoIpynbRenderer-0.0.2.dist-info/WHEEL
videoIpynbRenderer-0.0.2.dist-info/top_level.txt
videoIpynbRenderer-0.0.2.dist-info/RECORD
