Metadata-Version: 2.1
Name: videoIpynbRenderer
Version: 0.0.2
Summary: a small python package
Home-page: https://github.com/SoumitSarkar/videoIpynbRenderer
Author: SoumitSarkar
Author-email: sayhi2soumit@gmail.com
License: MIT
Project-URL: Bug Tracker, https://github.com/SoumitSarkar/videoIpynbRenderer/issues
Classifier: Programming Language :: Python :: 3.8
Classifier: Programming Language :: Python :: 3.9
Classifier: Programming Language :: Python :: 3.10
Classifier: Operating System :: OS Independent
Requires-Python: >=3.8
License-File: LICENSE
Requires-Dist: ensure (==1.0.2)
Requires-Dist: py-youtube (==1.1.7)
Provides-Extra: testing
Requires-Dist: pytest (>=7.2.1) ; extra == 'testing'
Requires-Dist: mypy (>=1.0.1) ; extra == 'testing'
Requires-Dist: flake8 (>=6.0.0) ; extra == 'testing'
Requires-Dist: tox (>=4.4.6) ; extra == 'testing'
Requires-Dist: black (>=23.1.0) ; extra == 'testing'
